[
  {
    "dimension": {
      "f_135804_": "minecraft",
      "f_135805_": "overworld"
    },
    "id": "b0dd26d1-48f8-414c-a9a5-9224540feb02",
    "ownerID": "e9e678c6-8774-30a2-9bf6-3c850d440fba",
    "pos": {
      "f_123285_": -174,
      "f_123286_": 115,
      "f_123289_": -264
    },
    "type": 0
  },
  {
    "dimension": {
      "f_135804_": "minecraft",
      "f_135805_": "overworld"
    },
    "id": "b42d3153-f8b2-413b-b0d2-d56523bea002",
    "ownerID": "e9e678c6-8774-30a2-9bf6-3c850d440fba",
    "pos": {
      "f_123285_": -9,
      "f_123286_": 70,
      "f_123289_": -13
    },
    "type": 0
  },
  {
    "dimension": {
      "f_135804_": "minecraft",
      "f_135805_": "overworld"
    },
    "id": "0860cfc2-a1f5-4a07-9675-1fa85d9db835",
    "ownerID": "61674e00-9cc2-392c-8ed7-e0a8a30a357c",
    "pos": {
      "f_123285_": 264,
      "f_123286_": 64,
      "f_123289_": 192
    },
    "type": 0
  },
  {
    "dimension": {
      "f_135804_": "minecraft",
      "f_135805_": "overworld"
    },
    "id": "4bd5f46f-80f9-4817-886f-de3d03e12eff",
    "ownerID": "214e3f06-265c-324f-89c0-a9758938228b",
    "pos": {
      "f_123285_": 60,
      "f_123286_": 72,
      "f_123289_": 0
    },
    "type": 0
  },
  {
    "dimension": {
      "f_135804_": "minecraft",
      "f_135805_": "overworld"
    },
    "id": "a17b75b1-ce68-4b6e-9fbe-42eff7841349",
    "ownerID": "214e3f06-265c-324f-89c0-a9758938228b",
    "pos": {
      "f_123285_": -218,
      "f_123286_": 116,
      "f_123289_": -291
    },
    "type": 0
  },
  {
    "dimension": {
      "f_135804_": "minecraft",
      "f_135805_": "overworld"
    },
    "id": "486baf6b-8bbb-42a7-8d5c-510508671c1c",
    "ownerID": "61674e00-9cc2-392c-8ed7-e0a8a30a357c",
    "pos": {
      "f_123285_": 745,
      "f_123286_": 82,
      "f_123289_": -96
    },
    "type": 0
  },
  {
    "dimension": {
      "f_135804_": "minecraft",
      "f_135805_": "overworld"
    },
    "id": "9a5bb675-9b59-4e4e-8ca0-8f1b3e2f84c8",
    "ownerID": "214e3f06-265c-324f-89c0-a9758938228b",
    "pos": {
      "f_123285_": -240,
      "f_123286_": 113,
      "f_123289_": -163
    },
    "type": 0
  },
  {
    "dimension": {
      "f_135804_": "minecraft",
      "f_135805_": "overworld"
    },
    "id": "19f03c80-24ce-49d8-81d1-6be34e309ca2",
    "ownerID": "214e3f06-265c-324f-89c0-a9758938228b",
    "pos": {
      "f_123285_": -8,
      "f_123286_": 69,
      "f_123289_": -32
    },
    "type": 0
  },
  {
    "dimension": {
      "f_135804_": "minecraft",
      "f_135805_": "overworld"
    },
    "id": "6dc42e13-2bc7-4a90-bdd7-622c1bae97df",
    "ownerID": "e9e678c6-8774-30a2-9bf6-3c850d440fba",
    "pos": {
      "f_123285_": 97,
      "f_123286_": 105,
      "f_123289_": -324
    },
    "type": 0
  },
  {
    "dimension": {
      "f_135804_": "minecraft",
      "f_135805_": "overworld"
    },
    "id": "660a1598-47a4-4a4a-aaa9-9d563cf45361",
    "ownerID": "61674e00-9cc2-392c-8ed7-e0a8a30a357c",
    "pos": {
      "f_123285_": 532,
      "f_123286_": 65,
      "f_123289_": 426
    },
    "type": 0
  },
  {
    "dimension": {
      "f_135804_": "minecraft",
      "f_135805_": "overworld"
    },
    "id": "a9b1ec56-69fe-41a5-8c97-1bf0bea76f33",
    "ownerID": "a66a6d6e-0e9e-3bc7-8330-0da175b101a1",
    "pos": {
      "f_123285_": 118,
      "f_123286_": 65,
      "f_123289_": 492
    },
    "type": 0
  },
  {
    "dimension": {
      "f_135804_": "minecraft",
      "f_135805_": "overworld"
    },
    "id": "d70c2c45-4d42-43ca-8662-7379198dc725",
    "ownerID": "214e3f06-265c-324f-89c0-a9758938228b",
    "pos": {
      "f_123285_": 1,
      "f_123286_": 73,
      "f_123289_": -3
    },
    "type": 0
  },
  {
    "dimension": {
      "f_135804_": "minecraft",
      "f_135805_": "overworld"
    },
    "id": "3c6ac3bc-2b4e-4cc9-83d5-d7c02f49047d",
    "ownerID": "a66a6d6e-0e9e-3bc7-8330-0da175b101a1",
    "pos": {
      "f_123285_": -6,
      "f_123286_": 70,
      "f_123289_": -13
    },
    "type": 0
  },
  {
    "dimension": {
      "f_135804_": "minecraft",
      "f_135805_": "overworld"
    },
    "id": "5b1df20a-63fc-4378-a7d2-449357dcc805",
    "ownerID": "3cad7924-9f5e-3626-b6f7-a9e4be20ff83",
    "pos": {
      "f_123285_": 408,
      "f_123286_": 65,
      "f_123289_": 369
    },
    "type": 0
  },
  {
    "dimension": {
      "f_135804_": "minecraft",
      "f_135805_": "overworld"
    },
    "id": "b7341ab3-d30a-454f-b4a6-2da5ea965aa5",
    "ownerID": "e9e678c6-8774-30a2-9bf6-3c850d440fba",
    "pos": {
      "f_123285_": 211,
      "f_123286_": 65,
      "f_123289_": 267
    },
    "type": 0
  },
  {
    "dimension": {
      "f_135804_": "minecraft",
      "f_135805_": "overworld"
    },
    "id": "15d914fa-cb92-4def-a5fe-551451a1b4ec",
    "ownerID": "214e3f06-265c-324f-89c0-a9758938228b",
    "pos": {
      "f_123285_": 75,
      "f_123286_": 64,
      "f_123289_": 213
    },
    "type": 0
  },
  {
    "dimension": {
      "f_135804_": "minecraft",
      "f_135805_": "overworld"
    },
    "id": "341c94b9-ca73-4a49-a2d1-23154ff295cd",
    "ownerID": "214e3f06-265c-324f-89c0-a9758938228b",
    "pos": {
      "f_123285_": 8,
      "f_123286_": 42,
      "f_123289_": -50
    },
    "type": 0
  },
  {
    "dimension": {
      "f_135804_": "minecraft",
      "f_135805_": "overworld"
    },
    "id": "688e2302-5b68-4e1b-8338-9d32c1078196",
    "ownerID": "3cad7924-9f5e-3626-b6f7-a9e4be20ff83",
    "pos": {
      "f_123285_": -81,
      "f_123286_": 27,
      "f_123289_": 274
    },
    "type": 0
  },
  {
    "dimension": {
      "f_135804_": "minecraft",
      "f_135805_": "overworld"
    },
    "id": "2c02c689-ffd6-4963-870a-f5cc282507bb",
    "ownerID": "61674e00-9cc2-392c-8ed7-e0a8a30a357c",
    "pos": {
      "f_123285_": 381,
      "f_123286_": 64,
      "f_123289_": -73
    },
    "type": 0
  },
  {
    "dimension": {
      "f_135804_": "minecraft",
      "f_135805_": "overworld"
    },
    "id": "56100805-3ea4-4566-9209-e6ecd2ac73c3",
    "ownerID": "61674e00-9cc2-392c-8ed7-e0a8a30a357c",
    "pos": {
      "f_123285_": 49,
      "f_123286_": 225,
      "f_123289_": 151
    },
    "type": 0
  },
  {
    "dimension": {
      "f_135804_": "minecraft",
      "f_135805_": "overworld"
    },
    "id": "256672a2-913a-4687-9091-a8ca2ab27227",
    "ownerID": "214e3f06-265c-324f-89c0-a9758938228b",
    "pos": {
      "f_123285_": -5,
      "f_123286_": 69,
      "f_123289_": -10
    },
    "type": 0
  },
  {
    "dimension": {
      "f_135804_": "minecraft",
      "f_135805_": "overworld"
    },
    "id": "072b63ad-419b-4879-8e88-b1f4906e6c43",
    "ownerID": "3cad7924-9f5e-3626-b6f7-a9e4be20ff83",
    "pos": {
      "f_123285_": -145,
      "f_123286_": 7,
      "f_123289_": 278
    },
    "type": 0
  },
  {
    "dimension": {
      "f_135804_": "minecraft",
      "f_135805_": "overworld"
    },
    "id": "f98d86cd-6d92-42a5-8ba4-b14fae8292e3",
    "ownerID": "61674e00-9cc2-392c-8ed7-e0a8a30a357c",
    "pos": {
      "f_123285_": 408,
      "f_123286_": 69,
      "f_123289_": 205
    },
    "type": 0
  },
  {
    "dimension": {
      "f_135804_": "minecraft",
      "f_135805_": "overworld"
    },
    "id": "e49d3d34-5536-4428-942e-f6b7fd6b1c27",
    "ownerID": "e9e678c6-8774-30a2-9bf6-3c850d440fba",
    "pos": {
      "f_123285_": -215,
      "f_123286_": 117,
      "f_123289_": -294
    },
    "type": 0
  },
  {
    "dimension": {
      "f_135804_": "minecraft",
      "f_135805_": "overworld"
    },
    "id": "21442439-3b21-4835-a2fc-57d124a2dce9",
    "ownerID": "214e3f06-265c-324f-89c0-a9758938228b",
    "pos": {
      "f_123285_": -1,
      "f_123286_": 47,
      "f_123289_": -53
    },
    "type": 0
  },
  {
    "dimension": {
      "f_135804_": "minecraft",
      "f_135805_": "overworld"
    },
    "id": "27874938-dd7b-4c0f-a77a-f2232033fd51",
    "ownerID": "e4440d27-40f9-36c3-9afd-6959726cc3c7",
    "pos": {
      "f_123285_": -1738,
      "f_123286_": 157,
      "f_123289_": 70
    },
    "type": 1
  }
]